{"id":"t57","title":"Get Up Jean","artist":"NuJean","artistId":"a-nujean","albumId":"alb-nujean-getup","albumTitle":"Get Up Jean","albumCoverUrl":"/covers/alb-nujean-getup.jpg","artistPhotoUrl":"/artists/a-nujean.jpg","lore":"NuJean's debut title track — written for the first warm-up lap around a roller rink before school, when the jeans still smell like detergent.","artistPersona":"Five-member Y2K k-pop girl group — every comeback fits like fresh denim, every hook sounds like a text you meant to send at midnight but sent at noon.","albumConcept":"NuJean's denim-bright debut — roller-rink mornings, bunny-mascot optimism, hooks that fit before the belt does.","energy":4,"tempo":112,"genre":"k-pop","genreSlug":"k-pop","artistSlug":"nujean","albumSlug":"get-up-jean","mood":"energetic","scene":"gym","filePath":"data/tracks/t57.mp3","introOffsetMs":null}