{"id":"t97","title":"Break Focus","artist":"Amen Rush","artistId":"a-amen-rush","albumId":"alb-amen-neuro-rep","albumTitle":"Neuro Rep","albumCoverUrl":"/covers/alb-amen-neuro-rep.jpg","artistPhotoUrl":"/artists/a-amen-rush.jpg","lore":"Deep-work DnB — Amen Rush kept the break steady and the reese bass just wobbly enough to stay awake.","artistPersona":"Neurofunk and drum-and-bass producer — every break is an amen chop, every bassline is a PR attempt. 174 BPM minimum.","albumConcept":"Amen Rush's neurofunk debut — amen breaks chopped for PRs, reese bass wobble for the last rep you didn't know you had.","energy":3,"tempo":170,"genre":"dnb","genreSlug":"dnb","artistSlug":"amen-rush","albumSlug":"neuro-rep","mood":"focused","scene":"focus","filePath":"data/tracks/t97.mp3","introOffsetMs":null}